b64to16/__init__.py
b64to16/__main__.py
b64to16/b64to16.py
b64to16/version.py
base64_to_hex_converter-0.4.1.dist-info/LICENSE
base64_to_hex_converter-0.4.1.dist-info/METADATA
base64_to_hex_converter-0.4.1.dist-info/WHEEL
base64_to_hex_converter-0.4.1.dist-info/top_level.txt
base64_to_hex_converter-0.4.1.dist-info/RECORD
